README.txt
setup.py
docs/HISTORY.txt
docs/LICENSE.GPL
docs/LICENSE.txt
qi/__init__.py
qi.xmpp.client.egg-info/PKG-INFO
qi.xmpp.client.egg-info/SOURCES.txt
qi.xmpp.client.egg-info/dependency_links.txt
qi.xmpp.client.egg-info/entry_points.txt
qi.xmpp.client.egg-info/namespace_packages.txt
qi.xmpp.client.egg-info/not-zip-safe
qi.xmpp.client.egg-info/paster_plugins.txt
qi.xmpp.client.egg-info/requires.txt
qi.xmpp.client.egg-info/top_level.txt
qi/xmpp/__init__.py
qi/xmpp/client/__init__.py
qi/xmpp/client/avatar.py
qi/xmpp/client/client.py
qi/xmpp/client/disco.py
qi/xmpp/client/errorCodes.py
qi/xmpp/client/filetransfer.py
qi/xmpp/client/ns.py
qi/xmpp/client/pingpong.py
qi/xmpp/client/roster.py
qi/xmpp/client/vCard.py
qi/xmpp/client/xmppComm.py