Metadata-Version: 1.0
Name: qi.xmpp.client
Version: 0.1
Summary: A basic xmpp client meant to serve as a base for others.
Home-page: http://chatblox.com/
Author: G. Gozadinos
Author-email: ggozad@qiweb.net
License: GPL
Keywords: xmpp bot twisted jabber
Platform: UNKNOWN
Classifier: Programming Language :: Python
Classifier: Topic :: Software Development :: Libraries :: Python Modules
